{
    "Tau_TES": {
        "dm_pt": {
            "dm:[1.0,1.0]": {
                "pt:[140,145]": {
                    "down": 0.9980000257492065, 
                    "up": 0.9980000257492065, 
                    "value": 0.9980000257492065
                }, 
                "pt:[40,45]": {
                    "down": 0.9980000257492065, 
                    "up": 0.9980000257492065, 
                    "value": 0.9980000257492065
                }, 
                "pt:[155,160]": {
                    "down": 0.9980000257492065, 
                    "up": 0.9980000257492065, 
                    "value": 0.9980000257492065
                }, 
                "pt:[85,90]": {
                    "down": 0.9980000257492065, 
                    "up": 0.9980000257492065, 
                    "value": 0.9980000257492065
                }, 
                "pt:[80,85]": {
                    "down": 0.9980000257492065, 
                    "up": 0.9980000257492065, 
                    "value": 0.9980000257492065
                }, 
                "pt:[90,95]": {
                    "down": 0.9980000257492065, 
                    "up": 0.9980000257492065, 
                    "value": 0.9980000257492065
                }, 
                "pt:[65,70]": {
                    "down": 0.9980000257492065, 
                    "up": 0.9980000257492065, 
                    "value": 0.9980000257492065
                }, 
                "pt:[75,80]": {
                    "down": 0.9980000257492065, 
                    "up": 0.9980000257492065, 
                    "value": 0.9980000257492065
                }, 
                "pt:[55,60]": {
                    "down": 0.9980000257492065, 
                    "up": 0.9980000257492065, 
                    "value": 0.9980000257492065
                }, 
                "pt:[25,30]": {
                    "down": 0.9980000257492065, 
                    "up": 0.9980000257492065, 
                    "value": 0.9980000257492065
                }, 
                "pt:[100,105]": {
                    "down": 0.9980000257492065, 
                    "up": 0.9980000257492065, 
                    "value": 0.9980000257492065
                }, 
                "pt:[160,165]": {
                    "down": 0.9980000257492065, 
                    "up": 0.9980000257492065, 
                    "value": 0.9980000257492065
                }, 
                "pt:[195,200]": {
                    "down": 0.9980000257492065, 
                    "up": 0.9980000257492065, 
                    "value": 0.9980000257492065
                }, 
                "pt:[200,205]": {
                    "down": 0.9980000257492065, 
                    "up": 0.9980000257492065, 
                    "value": 0.9980000257492065
                }, 
                "pt:[60,65]": {
                    "down": 0.9980000257492065, 
                    "up": 0.9980000257492065, 
                    "value": 0.9980000257492065
                }, 
                "pt:[10,15]": {
                    "down": 0.9980000257492065, 
                    "up": 0.9980000257492065, 
                    "value": 0.9980000257492065
                }, 
                "pt:[125,130]": {
                    "down": 0.9980000257492065, 
                    "up": 0.9980000257492065, 
                    "value": 0.9980000257492065
                }, 
                "pt:[45,50]": {
                    "down": 0.9980000257492065, 
                    "up": 0.9980000257492065, 
                    "value": 0.9980000257492065
                }, 
                "pt:[180,185]": {
                    "down": 0.9980000257492065, 
                    "up": 0.9980000257492065, 
                    "value": 0.9980000257492065
                }, 
                "pt:[115,120]": {
                    "down": 0.9980000257492065, 
                    "up": 0.9980000257492065, 
                    "value": 0.9980000257492065
                }, 
                "pt:[190,195]": {
                    "down": 0.9980000257492065, 
                    "up": 0.9980000257492065, 
                    "value": 0.9980000257492065
                }, 
                "pt:[145,150]": {
                    "down": 0.9980000257492065, 
                    "up": 0.9980000257492065, 
                    "value": 0.9980000257492065
                }, 
                "pt:[135,140]": {
                    "down": 0.9980000257492065, 
                    "up": 0.9980000257492065, 
                    "value": 0.9980000257492065
                }, 
                "pt:[50,55]": {
                    "down": 0.9980000257492065, 
                    "up": 0.9980000257492065, 
                    "value": 0.9980000257492065
                }, 
                "pt:[70,75]": {
                    "down": 0.9980000257492065, 
                    "up": 0.9980000257492065, 
                    "value": 0.9980000257492065
                }, 
                "pt:[110,115]": {
                    "down": 0.9980000257492065, 
                    "up": 0.9980000257492065, 
                    "value": 0.9980000257492065
                }, 
                "pt:[165,170]": {
                    "down": 0.9980000257492065, 
                    "up": 0.9980000257492065, 
                    "value": 0.9980000257492065
                }, 
                "pt:[95,100]": {
                    "down": 0.9980000257492065, 
                    "up": 0.9980000257492065, 
                    "value": 0.9980000257492065
                }, 
                "pt:[175,180]": {
                    "down": 0.9980000257492065, 
                    "up": 0.9980000257492065, 
                    "value": 0.9980000257492065
                }, 
                "pt:[15,20]": {
                    "down": 0.9980000257492065, 
                    "up": 0.9980000257492065, 
                    "value": 0.9980000257492065
                }, 
                "pt:[30,35]": {
                    "down": 0.9980000257492065, 
                    "up": 0.9980000257492065, 
                    "value": 0.9980000257492065
                }, 
                "pt:[120,125]": {
                    "down": 0.9980000257492065, 
                    "up": 0.9980000257492065, 
                    "value": 0.9980000257492065
                }, 
                "pt:[185,190]": {
                    "down": 0.9980000257492065, 
                    "up": 0.9980000257492065, 
                    "value": 0.9980000257492065
                }, 
                "pt:[150,155]": {
                    "down": 0.9980000257492065, 
                    "up": 0.9980000257492065, 
                    "value": 0.9980000257492065
                }, 
                "pt:[130,135]": {
                    "down": 0.9980000257492065, 
                    "up": 0.9980000257492065, 
                    "value": 0.9980000257492065
                }, 
                "pt:[20,25]": {
                    "down": 0.9980000257492065, 
                    "up": 0.9980000257492065, 
                    "value": 0.9980000257492065
                }, 
                "pt:[35,40]": {
                    "down": 0.9980000257492065, 
                    "up": 0.9980000257492065, 
                    "value": 0.9980000257492065
                }, 
                "pt:[105,110]": {
                    "down": 0.9980000257492065, 
                    "up": 0.9980000257492065, 
                    "value": 0.9980000257492065
                }, 
                "pt:[170,175]": {
                    "down": 0.9980000257492065, 
                    "up": 0.9980000257492065, 
                    "value": 0.9980000257492065
                }
            }, 
            "dm:[11.0,11.0]": {
                "pt:[140,145]": {
                    "down": 0.9990000128746033, 
                    "up": 0.9990000128746033, 
                    "value": 0.9990000128746033
                }, 
                "pt:[40,45]": {
                    "down": 0.9990000128746033, 
                    "up": 0.9990000128746033, 
                    "value": 0.9990000128746033
                }, 
                "pt:[155,160]": {
                    "down": 0.9990000128746033, 
                    "up": 0.9990000128746033, 
                    "value": 0.9990000128746033
                }, 
                "pt:[85,90]": {
                    "down": 0.9990000128746033, 
                    "up": 0.9990000128746033, 
                    "value": 0.9990000128746033
                }, 
                "pt:[80,85]": {
                    "down": 0.9990000128746033, 
                    "up": 0.9990000128746033, 
                    "value": 0.9990000128746033
                }, 
                "pt:[90,95]": {
                    "down": 0.9990000128746033, 
                    "up": 0.9990000128746033, 
                    "value": 0.9990000128746033
                }, 
                "pt:[65,70]": {
                    "down": 0.9990000128746033, 
                    "up": 0.9990000128746033, 
                    "value": 0.9990000128746033
                }, 
                "pt:[75,80]": {
                    "down": 0.9990000128746033, 
                    "up": 0.9990000128746033, 
                    "value": 0.9990000128746033
                }, 
                "pt:[55,60]": {
                    "down": 0.9990000128746033, 
                    "up": 0.9990000128746033, 
                    "value": 0.9990000128746033
                }, 
                "pt:[25,30]": {
                    "down": 0.9990000128746033, 
                    "up": 0.9990000128746033, 
                    "value": 0.9990000128746033
                }, 
                "pt:[100,105]": {
                    "down": 0.9990000128746033, 
                    "up": 0.9990000128746033, 
                    "value": 0.9990000128746033
                }, 
                "pt:[160,165]": {
                    "down": 0.9990000128746033, 
                    "up": 0.9990000128746033, 
                    "value": 0.9990000128746033
                }, 
                "pt:[195,200]": {
                    "down": 0.9990000128746033, 
                    "up": 0.9990000128746033, 
                    "value": 0.9990000128746033
                }, 
                "pt:[200,205]": {
                    "down": 0.9990000128746033, 
                    "up": 0.9990000128746033, 
                    "value": 0.9990000128746033
                }, 
                "pt:[60,65]": {
                    "down": 0.9990000128746033, 
                    "up": 0.9990000128746033, 
                    "value": 0.9990000128746033
                }, 
                "pt:[10,15]": {
                    "down": 0.9990000128746033, 
                    "up": 0.9990000128746033, 
                    "value": 0.9990000128746033
                }, 
                "pt:[125,130]": {
                    "down": 0.9990000128746033, 
                    "up": 0.9990000128746033, 
                    "value": 0.9990000128746033
                }, 
                "pt:[45,50]": {
                    "down": 0.9990000128746033, 
                    "up": 0.9990000128746033, 
                    "value": 0.9990000128746033
                }, 
                "pt:[180,185]": {
                    "down": 0.9990000128746033, 
                    "up": 0.9990000128746033, 
                    "value": 0.9990000128746033
                }, 
                "pt:[115,120]": {
                    "down": 0.9990000128746033, 
                    "up": 0.9990000128746033, 
                    "value": 0.9990000128746033
                }, 
                "pt:[190,195]": {
                    "down": 0.9990000128746033, 
                    "up": 0.9990000128746033, 
                    "value": 0.9990000128746033
                }, 
                "pt:[145,150]": {
                    "down": 0.9990000128746033, 
                    "up": 0.9990000128746033, 
                    "value": 0.9990000128746033
                }, 
                "pt:[135,140]": {
                    "down": 0.9990000128746033, 
                    "up": 0.9990000128746033, 
                    "value": 0.9990000128746033
                }, 
                "pt:[50,55]": {
                    "down": 0.9990000128746033, 
                    "up": 0.9990000128746033, 
                    "value": 0.9990000128746033
                }, 
                "pt:[70,75]": {
                    "down": 0.9990000128746033, 
                    "up": 0.9990000128746033, 
                    "value": 0.9990000128746033
                }, 
                "pt:[110,115]": {
                    "down": 0.9990000128746033, 
                    "up": 0.9990000128746033, 
                    "value": 0.9990000128746033
                }, 
                "pt:[165,170]": {
                    "down": 0.9990000128746033, 
                    "up": 0.9990000128746033, 
                    "value": 0.9990000128746033
                }, 
                "pt:[95,100]": {
                    "down": 0.9990000128746033, 
                    "up": 0.9990000128746033, 
                    "value": 0.9990000128746033
                }, 
                "pt:[175,180]": {
                    "down": 0.9990000128746033, 
                    "up": 0.9990000128746033, 
                    "value": 0.9990000128746033
                }, 
                "pt:[15,20]": {
                    "down": 0.9990000128746033, 
                    "up": 0.9990000128746033, 
                    "value": 0.9990000128746033
                }, 
                "pt:[30,35]": {
                    "down": 0.9990000128746033, 
                    "up": 0.9990000128746033, 
                    "value": 0.9990000128746033
                }, 
                "pt:[120,125]": {
                    "down": 0.9990000128746033, 
                    "up": 0.9990000128746033, 
                    "value": 0.9990000128746033
                }, 
                "pt:[185,190]": {
                    "down": 0.9990000128746033, 
                    "up": 0.9990000128746033, 
                    "value": 0.9990000128746033
                }, 
                "pt:[150,155]": {
                    "down": 0.9990000128746033, 
                    "up": 0.9990000128746033, 
                    "value": 0.9990000128746033
                }, 
                "pt:[130,135]": {
                    "down": 0.9990000128746033, 
                    "up": 0.9990000128746033, 
                    "value": 0.9990000128746033
                }, 
                "pt:[20,25]": {
                    "down": 0.9990000128746033, 
                    "up": 0.9990000128746033, 
                    "value": 0.9990000128746033
                }, 
                "pt:[35,40]": {
                    "down": 0.9990000128746033, 
                    "up": 0.9990000128746033, 
                    "value": 0.9990000128746033
                }, 
                "pt:[105,110]": {
                    "down": 0.9990000128746033, 
                    "up": 0.9990000128746033, 
                    "value": 0.9990000128746033
                }, 
                "pt:[170,175]": {
                    "down": 0.9990000128746033, 
                    "up": 0.9990000128746033, 
                    "value": 0.9990000128746033
                }
            }, 
            "dm:[0.0,0.0]": {
                "pt:[140,145]": {
                    "down": 0.9869999885559082, 
                    "up": 0.9869999885559082, 
                    "value": 0.9869999885559082
                }, 
                "pt:[40,45]": {
                    "down": 0.9869999885559082, 
                    "up": 0.9869999885559082, 
                    "value": 0.9869999885559082
                }, 
                "pt:[155,160]": {
                    "down": 0.9869999885559082, 
                    "up": 0.9869999885559082, 
                    "value": 0.9869999885559082
                }, 
                "pt:[85,90]": {
                    "down": 0.9869999885559082, 
                    "up": 0.9869999885559082, 
                    "value": 0.9869999885559082
                }, 
                "pt:[80,85]": {
                    "down": 0.9869999885559082, 
                    "up": 0.9869999885559082, 
                    "value": 0.9869999885559082
                }, 
                "pt:[90,95]": {
                    "down": 0.9869999885559082, 
                    "up": 0.9869999885559082, 
                    "value": 0.9869999885559082
                }, 
                "pt:[65,70]": {
                    "down": 0.9869999885559082, 
                    "up": 0.9869999885559082, 
                    "value": 0.9869999885559082
                }, 
                "pt:[75,80]": {
                    "down": 0.9869999885559082, 
                    "up": 0.9869999885559082, 
                    "value": 0.9869999885559082
                }, 
                "pt:[55,60]": {
                    "down": 0.9869999885559082, 
                    "up": 0.9869999885559082, 
                    "value": 0.9869999885559082
                }, 
                "pt:[25,30]": {
                    "down": 0.9869999885559082, 
                    "up": 0.9869999885559082, 
                    "value": 0.9869999885559082
                }, 
                "pt:[100,105]": {
                    "down": 0.9869999885559082, 
                    "up": 0.9869999885559082, 
                    "value": 0.9869999885559082
                }, 
                "pt:[160,165]": {
                    "down": 0.9869999885559082, 
                    "up": 0.9869999885559082, 
                    "value": 0.9869999885559082
                }, 
                "pt:[195,200]": {
                    "down": 0.9869999885559082, 
                    "up": 0.9869999885559082, 
                    "value": 0.9869999885559082
                }, 
                "pt:[200,205]": {
                    "down": 0.9869999885559082, 
                    "up": 0.9869999885559082, 
                    "value": 0.9869999885559082
                }, 
                "pt:[60,65]": {
                    "down": 0.9869999885559082, 
                    "up": 0.9869999885559082, 
                    "value": 0.9869999885559082
                }, 
                "pt:[10,15]": {
                    "down": 0.9869999885559082, 
                    "up": 0.9869999885559082, 
                    "value": 0.9869999885559082
                }, 
                "pt:[125,130]": {
                    "down": 0.9869999885559082, 
                    "up": 0.9869999885559082, 
                    "value": 0.9869999885559082
                }, 
                "pt:[45,50]": {
                    "down": 0.9869999885559082, 
                    "up": 0.9869999885559082, 
                    "value": 0.9869999885559082
                }, 
                "pt:[180,185]": {
                    "down": 0.9869999885559082, 
                    "up": 0.9869999885559082, 
                    "value": 0.9869999885559082
                }, 
                "pt:[115,120]": {
                    "down": 0.9869999885559082, 
                    "up": 0.9869999885559082, 
                    "value": 0.9869999885559082
                }, 
                "pt:[190,195]": {
                    "down": 0.9869999885559082, 
                    "up": 0.9869999885559082, 
                    "value": 0.9869999885559082
                }, 
                "pt:[145,150]": {
                    "down": 0.9869999885559082, 
                    "up": 0.9869999885559082, 
                    "value": 0.9869999885559082
                }, 
                "pt:[135,140]": {
                    "down": 0.9869999885559082, 
                    "up": 0.9869999885559082, 
                    "value": 0.9869999885559082
                }, 
                "pt:[50,55]": {
                    "down": 0.9869999885559082, 
                    "up": 0.9869999885559082, 
                    "value": 0.9869999885559082
                }, 
                "pt:[70,75]": {
                    "down": 0.9869999885559082, 
                    "up": 0.9869999885559082, 
                    "value": 0.9869999885559082
                }, 
                "pt:[110,115]": {
                    "down": 0.9869999885559082, 
                    "up": 0.9869999885559082, 
                    "value": 0.9869999885559082
                }, 
                "pt:[165,170]": {
                    "down": 0.9869999885559082, 
                    "up": 0.9869999885559082, 
                    "value": 0.9869999885559082
                }, 
                "pt:[95,100]": {
                    "down": 0.9869999885559082, 
                    "up": 0.9869999885559082, 
                    "value": 0.9869999885559082
                }, 
                "pt:[175,180]": {
                    "down": 0.9869999885559082, 
                    "up": 0.9869999885559082, 
                    "value": 0.9869999885559082
                }, 
                "pt:[15,20]": {
                    "down": 0.9869999885559082, 
                    "up": 0.9869999885559082, 
                    "value": 0.9869999885559082
                }, 
                "pt:[30,35]": {
                    "down": 0.9869999885559082, 
                    "up": 0.9869999885559082, 
                    "value": 0.9869999885559082
                }, 
                "pt:[120,125]": {
                    "down": 0.9869999885559082, 
                    "up": 0.9869999885559082, 
                    "value": 0.9869999885559082
                }, 
                "pt:[185,190]": {
                    "down": 0.9869999885559082, 
                    "up": 0.9869999885559082, 
                    "value": 0.9869999885559082
                }, 
                "pt:[150,155]": {
                    "down": 0.9869999885559082, 
                    "up": 0.9869999885559082, 
                    "value": 0.9869999885559082
                }, 
                "pt:[130,135]": {
                    "down": 0.9869999885559082, 
                    "up": 0.9869999885559082, 
                    "value": 0.9869999885559082
                }, 
                "pt:[20,25]": {
                    "down": 0.9869999885559082, 
                    "up": 0.9869999885559082, 
                    "value": 0.9869999885559082
                }, 
                "pt:[35,40]": {
                    "down": 0.9869999885559082, 
                    "up": 0.9869999885559082, 
                    "value": 0.9869999885559082
                }, 
                "pt:[105,110]": {
                    "down": 0.9869999885559082, 
                    "up": 0.9869999885559082, 
                    "value": 0.9869999885559082
                }, 
                "pt:[170,175]": {
                    "down": 0.9869999885559082, 
                    "up": 0.9869999885559082, 
                    "value": 0.9869999885559082
                }
            }, 
            "dm:[10.0,10.0]": {
                "pt:[140,145]": {
                    "down": 0.984000027179718, 
                    "up": 0.984000027179718, 
                    "value": 0.984000027179718
                }, 
                "pt:[40,45]": {
                    "down": 0.984000027179718, 
                    "up": 0.984000027179718, 
                    "value": 0.984000027179718
                }, 
                "pt:[155,160]": {
                    "down": 0.984000027179718, 
                    "up": 0.984000027179718, 
                    "value": 0.984000027179718
                }, 
                "pt:[85,90]": {
                    "down": 0.984000027179718, 
                    "up": 0.984000027179718, 
                    "value": 0.984000027179718
                }, 
                "pt:[80,85]": {
                    "down": 0.984000027179718, 
                    "up": 0.984000027179718, 
                    "value": 0.984000027179718
                }, 
                "pt:[90,95]": {
                    "down": 0.984000027179718, 
                    "up": 0.984000027179718, 
                    "value": 0.984000027179718
                }, 
                "pt:[65,70]": {
                    "down": 0.984000027179718, 
                    "up": 0.984000027179718, 
                    "value": 0.984000027179718
                }, 
                "pt:[75,80]": {
                    "down": 0.984000027179718, 
                    "up": 0.984000027179718, 
                    "value": 0.984000027179718
                }, 
                "pt:[55,60]": {
                    "down": 0.984000027179718, 
                    "up": 0.984000027179718, 
                    "value": 0.984000027179718
                }, 
                "pt:[25,30]": {
                    "down": 0.984000027179718, 
                    "up": 0.984000027179718, 
                    "value": 0.984000027179718
                }, 
                "pt:[100,105]": {
                    "down": 0.984000027179718, 
                    "up": 0.984000027179718, 
                    "value": 0.984000027179718
                }, 
                "pt:[160,165]": {
                    "down": 0.984000027179718, 
                    "up": 0.984000027179718, 
                    "value": 0.984000027179718
                }, 
                "pt:[195,200]": {
                    "down": 0.984000027179718, 
                    "up": 0.984000027179718, 
                    "value": 0.984000027179718
                }, 
                "pt:[200,205]": {
                    "down": 0.984000027179718, 
                    "up": 0.984000027179718, 
                    "value": 0.984000027179718
                }, 
                "pt:[60,65]": {
                    "down": 0.984000027179718, 
                    "up": 0.984000027179718, 
                    "value": 0.984000027179718
                }, 
                "pt:[10,15]": {
                    "down": 0.984000027179718, 
                    "up": 0.984000027179718, 
                    "value": 0.984000027179718
                }, 
                "pt:[125,130]": {
                    "down": 0.984000027179718, 
                    "up": 0.984000027179718, 
                    "value": 0.984000027179718
                }, 
                "pt:[45,50]": {
                    "down": 0.984000027179718, 
                    "up": 0.984000027179718, 
                    "value": 0.984000027179718
                }, 
                "pt:[180,185]": {
                    "down": 0.984000027179718, 
                    "up": 0.984000027179718, 
                    "value": 0.984000027179718
                }, 
                "pt:[115,120]": {
                    "down": 0.984000027179718, 
                    "up": 0.984000027179718, 
                    "value": 0.984000027179718
                }, 
                "pt:[190,195]": {
                    "down": 0.984000027179718, 
                    "up": 0.984000027179718, 
                    "value": 0.984000027179718
                }, 
                "pt:[145,150]": {
                    "down": 0.984000027179718, 
                    "up": 0.984000027179718, 
                    "value": 0.984000027179718
                }, 
                "pt:[135,140]": {
                    "down": 0.984000027179718, 
                    "up": 0.984000027179718, 
                    "value": 0.984000027179718
                }, 
                "pt:[50,55]": {
                    "down": 0.984000027179718, 
                    "up": 0.984000027179718, 
                    "value": 0.984000027179718
                }, 
                "pt:[70,75]": {
                    "down": 0.984000027179718, 
                    "up": 0.984000027179718, 
                    "value": 0.984000027179718
                }, 
                "pt:[110,115]": {
                    "down": 0.984000027179718, 
                    "up": 0.984000027179718, 
                    "value": 0.984000027179718
                }, 
                "pt:[165,170]": {
                    "down": 0.984000027179718, 
                    "up": 0.984000027179718, 
                    "value": 0.984000027179718
                }, 
                "pt:[95,100]": {
                    "down": 0.984000027179718, 
                    "up": 0.984000027179718, 
                    "value": 0.984000027179718
                }, 
                "pt:[175,180]": {
                    "down": 0.984000027179718, 
                    "up": 0.984000027179718, 
                    "value": 0.984000027179718
                }, 
                "pt:[15,20]": {
                    "down": 0.984000027179718, 
                    "up": 0.984000027179718, 
                    "value": 0.984000027179718
                }, 
                "pt:[30,35]": {
                    "down": 0.984000027179718, 
                    "up": 0.984000027179718, 
                    "value": 0.984000027179718
                }, 
                "pt:[120,125]": {
                    "down": 0.984000027179718, 
                    "up": 0.984000027179718, 
                    "value": 0.984000027179718
                }, 
                "pt:[185,190]": {
                    "down": 0.984000027179718, 
                    "up": 0.984000027179718, 
                    "value": 0.984000027179718
                }, 
                "pt:[150,155]": {
                    "down": 0.984000027179718, 
                    "up": 0.984000027179718, 
                    "value": 0.984000027179718
                }, 
                "pt:[130,135]": {
                    "down": 0.984000027179718, 
                    "up": 0.984000027179718, 
                    "value": 0.984000027179718
                }, 
                "pt:[20,25]": {
                    "down": 0.984000027179718, 
                    "up": 0.984000027179718, 
                    "value": 0.984000027179718
                }, 
                "pt:[35,40]": {
                    "down": 0.984000027179718, 
                    "up": 0.984000027179718, 
                    "value": 0.984000027179718
                }, 
                "pt:[105,110]": {
                    "down": 0.984000027179718, 
                    "up": 0.984000027179718, 
                    "value": 0.984000027179718
                }, 
                "pt:[170,175]": {
                    "down": 0.984000027179718, 
                    "up": 0.984000027179718, 
                    "value": 0.984000027179718
                }
            }
        }
    }
}