{
    "NUM_HighPtID_DEN_TrackerMuons": {
        "abseta_pt": {
            "abseta:[0.0,0.9]": {
                "pt:[15,20]": {
                    "AltSig": 0.00040221780184113154,
                    "massBin": 0.00047996543525613555,
                    "massRange": 0.0001038350410270672,
                    "stat": 0.0011100306132732058,
                    "syst": 0.005118594167747403,
                    "tagIso": 0.0050790824524902245,
                    "value": 0.993236196504075
                },
                "pt:[20,25]": {
                    "AltSig": 0.00030376607365767416,
                    "massBin": 8.692584246045021e-05,
                    "massRange": 4.042465311038246e-05,
                    "stat": 0.0005717813868987121,
                    "syst": 0.0029163772316544993,
                    "tagIso": 0.0028989294705357715,
                    "value": 0.9918143488019201
                },
                "pt:[25,30]": {
                    "AltSig": 0.00025816232392750216,
                    "massBin": 0.00021859579143118646,
                    "massRange": 3.131998274163994e-05,
                    "stat": 0.0003539238357035001,
                    "syst": 0.00309682627788586,
                    "tagIso": 0.0030781358236046663,
                    "value": 0.9913919924697726
                },
                "pt:[30,40]": {
                    "AltSig": 5.964725316820463e-05,
                    "massBin": 6.066698425855055e-05,
                    "massRange": 3.578008692817214e-05,
                    "stat": 0.00015908771954254106,
                    "syst": 0.0031695758405877886,
                    "tagIso": 0.0031682317650114644,
                    "value": 0.9910490782204643
                },
                "pt:[40,50]": {
                    "AltSig": 8.512740115873552e-05,
                    "massBin": 2.2603367451690115e-05,
                    "massRange": 0.00017051752667834874,
                    "stat": 0.00014098265355477237,
                    "syst": 0.0030740318738337025,
                    "tagIso": 0.0030680349000284934,
                    "value": 0.9911022822000698
                },
                "pt:[50,60]": {
                    "AltSig": 0.0008327008501594069,
                    "massBin": 0.0002097284644355102,
                    "massRange": 0.00019547494384991593,
                    "stat": 0.0002930772055835726,
                    "syst": 0.003165319672730227,
                    "tagIso": 0.003040339034096229,
                    "value": 0.9900751160186981
                },
                "pt:[60,120]": {
                    "AltSig": 0.0004647527364221027,
                    "massBin": 0.00027134718275195757,
                    "massRange": 0.00010265106260426426,
                    "stat": 0.00045141360785800336,
                    "syst": 0.0024778177665846376,
                    "tagIso": 0.0024164890324910315,
                    "value": 0.9898655916679472
                }
            },
            "abseta:[0.9,1.2]": {
                "pt:[15,20]": {
                    "AltSig": 0.0001962423519350498,
                    "massBin": 0.000994723525231056,
                    "massRange": 0.00028077805751614004,
                    "stat": 0.001309595790253525,
                    "syst": 0.0047979522941485366,
                    "tagIso": 0.004681188305014183,
                    "value": 0.9867533546681378
                },
                "pt:[20,25]": {
                    "AltSig": 0.0006030219897112943,
                    "massBin": 0.0009471271700970396,
                    "massRange": 0.00026774817167468656,
                    "stat": 0.000779344735606454,
                    "syst": 0.005582124404128016,
                    "tagIso": 0.005461477673973869,
                    "value": 0.9867813447091118
                },
                "pt:[25,30]": {
                    "AltSig": 0.0007877119379868791,
                    "massBin": 0.0008126231042343557,
                    "massRange": 0.0003809940474214235,
                    "stat": 0.0005153653031731587,
                    "syst": 0.004473492409004144,
                    "tagIso": 0.0043111635856766806,
                    "value": 0.9888667914411796
                },
                "pt:[30,40]": {
                    "AltSig": 0.0008382469055582265,
                    "massBin": 0.00028814752968620017,
                    "massRange": 0.0003445599998155857,
                    "stat": 0.0002501772972883304,
                    "syst": 0.003550769946077481,
                    "tagIso": 0.003421046439753772,
                    "value": 0.9871046291484241
                },
                "pt:[40,50]": {
                    "AltSig": 6.944811103481996e-05,
                    "massBin": 2.4035892915108548e-05,
                    "massRange": 5.220844615799747e-05,
                    "stat": 0.00017009892638089106,
                    "syst": 0.00322893099419081,
                    "tagIso": 0.0032276723624186654,
                    "value": 0.9876300310309243
                },
                "pt:[50,60]": {
                    "AltSig": 0.0008907641384793274,
                    "massBin": 0.0008693172314425124,
                    "massRange": 0.00025693695758921553,
                    "stat": 0.0004557086941229164,
                    "syst": 0.0035197505536906848,
                    "tagIso": 0.003282294039349154,
                    "value": 0.987451733466811
                },
                "pt:[60,120]": {
                    "AltSig": 0.0002176902820186788,
                    "massBin": 0.0009638520664674299,
                    "massRange": 0.00026965685847424314,
                    "stat": 0.0006975134384406361,
                    "syst": 0.0018502106737019336,
                    "tagIso": 0.0015408325187506455,
                    "value": 0.9874427039656329
                }
            },
            "abseta:[1.2,2.1]": {
                "pt:[15,20]": {
                    "AltSig": 0.0009453744036547196,
                    "massBin": 0.0005749076647796336,
                    "massRange": 0.00035263993644452096,
                    "stat": 0.0004897520281199289,
                    "syst": 0.005335609221311594,
                    "tagIso": 0.005207698076085232,
                    "value": 0.9922168616752363
                },
                "pt:[20,25]": {
                    "AltSig": 0.0009554033642664717,
                    "massBin": 0.0005591826379375275,
                    "massRange": 0.00023022406445888377,
                    "stat": 0.0002433994274306822,
                    "syst": 0.0038845906879754867,
                    "tagIso": 0.0037163908408868185,
                    "value": 0.9913369853559548
                },
                "pt:[25,30]": {
                    "AltSig": 0.0005155177377808018,
                    "massBin": 0.00024310084545831057,
                    "massRange": 0.00010094019246081887,
                    "stat": 0.00022147457332247507,
                    "syst": 0.00428419376343901,
                    "tagIso": 0.004244911155867281,
                    "value": 0.9927468959772348
                },
                "pt:[30,40]": {
                    "AltSig": 0.0003196715221651658,
                    "massBin": 7.249611000742506e-05,
                    "massRange": 2.825904301018145e-05,
                    "stat": 0.00011344411639682383,
                    "syst": 0.003902400774159137,
                    "tagIso": 0.0038885071249255,
                    "value": 0.9925793213355351
                },
                "pt:[40,50]": {
                    "AltSig": 0.00012148965069014306,
                    "massBin": 2.305627683796274e-05,
                    "massRange": 1.4331979796278205e-05,
                    "stat": 0.00010117227680326487,
                    "syst": 0.003004491064184378,
                    "tagIso": 0.0030019110283271977,
                    "value": 0.9935578692142651
                },
                "pt:[50,60]": {
                    "AltSig": 0.0014368966516998816,
                    "massBin": 0.0005363181625781532,
                    "massRange": 0.00011269897814664143,
                    "stat": 0.00021908602603235459,
                    "syst": 0.0030524255569365348,
                    "tagIso": 0.00263671984893854,
                    "value": 0.9930858683423
                },
                "pt:[60,120]": {
                    "AltSig": 0.0007120789561055885,
                    "massBin": 1.2331072381355224e-05,
                    "massRange": 9.328630316712827e-05,
                    "stat": 0.0003494803528952623,
                    "syst": 0.0020955939400868445,
                    "tagIso": 0.0019686551582985823,
                    "value": 0.993122132080292
                }
            },
            "abseta:[2.1,2.4]": {
                "pt:[15,20]": {
                    "AltSig": 0.0034287432983332033,
                    "massBin": 0.0015449417771291052,
                    "massRange": 0.001202190042370932,
                    "stat": 0.0015824962540245502,
                    "syst": 0.006312087262098773,
                    "tagIso": 0.004924841013250081,
                    "value": 0.9793646636506558
                },
                "pt:[20,25]": {
                    "AltSig": 0.0016950029464880556,
                    "massBin": 0.0005010437281423585,
                    "massRange": 0.0008665952514442798,
                    "stat": 0.0010293101546629997,
                    "syst": 0.0057614757513353735,
                    "tagIso": 0.005414751674572504,
                    "value": 0.980486044272866
                },
                "pt:[25,30]": {
                    "AltSig": 0.002806689007248453,
                    "massBin": 4.632202286314335e-05,
                    "massRange": 0.0006068920368090258,
                    "stat": 0.0007223296061120292,
                    "syst": 0.005689808287800589,
                    "tagIso": 0.004911817534718754,
                    "value": 0.9789820644221303
                },
                "pt:[30,40]": {
                    "AltSig": 0.0018079448991283886,
                    "massBin": 5.664195451565712e-05,
                    "massRange": 0.00022924173049332364,
                    "stat": 0.0003970461833790688,
                    "syst": 0.0048723142255964365,
                    "tagIso": 0.004518298470957194,
                    "value": 0.9796192221894258
                },
                "pt:[40,50]": {
                    "AltSig": 0.0018785086316747135,
                    "massBin": 4.2862506418106516e-05,
                    "massRange": 0.00010255407624243373,
                    "stat": 0.00044981238620889365,
                    "syst": 0.003977472365111249,
                    "tagIso": 0.0035041599853512517,
                    "value": 0.9796343526745811
                },
                "pt:[50,60]": {
                    "AltSig": 0.0054824319412740685,
                    "massBin": 0.0002819430212555041,
                    "massRange": 0.00028073748016954614,
                    "stat": 0.0009752832744215038,
                    "syst": 0.0065150709910998614,
                    "tagIso": 0.003497253869589989,
                    "value": 0.977748406429262
                },
                "pt:[60,120]": {
                    "AltSig": 0.008164931153726629,
                    "massBin": 0.0002647886510711017,
                    "massRange": 0.0009768924683288827,
                    "stat": 0.0016861368353318135,
                    "syst": 0.01265355154298459,
                    "tagIso": 0.009613627514183098,
                    "value": 0.9755794039779263
                }
            }
        }
    },
    "NUM_LooseID_DEN_TrackerMuons": {
        "abseta_pt": {
            "abseta:[0.0,0.9]": {
                "pt:[15,20]": {
                    "AltSig": 0.00042318048463385605,
                    "massBin": 0.00019306420530140755,
                    "massRange": 0.00012104565017362345,
                    "stat": 0.0005912667969425002,
                    "syst": 0.0005276457468994988,
                    "tagIso": 0.00021772109418144447,
                    "value": 0.9995262787548511
                },
                "pt:[20,25]": {
                    "AltSig": 1.873205260649602e-05,
                    "massBin": 5.762232516248744e-05,
                    "massRange": 9.935241905123515e-05,
                    "stat": 0.00024825796281629196,
                    "syst": 0.00014044163446788873,
                    "tagIso": 7.862396179725284e-05,
                    "value": 0.9988270595559574
                },
                "pt:[25,30]": {
                    "AltSig": 4.401936559095265e-05,
                    "massBin": 4.3707240601376096e-05,
                    "massRange": 2.2414641746515418e-05,
                    "stat": 0.00011593606880079812,
                    "syst": 0.00010305890950906301,
                    "tagIso": 7.918772150122821e-05,
                    "value": 0.9991221082864226
                },
                "pt:[30,40]": {
                    "AltSig": 2.8938717109072698e-05,
                    "massBin": 1.452139635871319e-05,
                    "massRange": 2.516204840846692e-05,
                    "stat": 4.191856833110352e-05,
                    "syst": 4.388568258424525e-05,
                    "tagIso": 1.5636628653559193e-05,
                    "value": 0.9991171655491334
                },
                "pt:[40,50]": {
                    "AltSig": 2.2410677061768247e-05,
                    "massBin": 8.989235452006028e-06,
                    "massRange": 1.4796034074615605e-05,
                    "stat": 3.315379112173905e-05,
                    "syst": 2.8567326869927497e-05,
                    "tagIso": 3.7582894749643714e-06,
                    "value": 0.9991970841493998
                },
                "pt:[50,60]": {
                    "AltSig": 9.840434793018105e-06,
                    "massBin": 3.482747703725808e-05,
                    "massRange": 4.3312415984153585e-05,
                    "stat": 7.441430422473623e-05,
                    "syst": 5.670742797595905e-05,
                    "tagIso": 5.475371728735912e-06,
                    "value": 0.999065638173131
                },
                "pt:[60,120]": {
                    "AltSig": 0.00014112477977190618,
                    "massBin": 0.00011075004688815282,
                    "massRange": 2.6552851319028292e-05,
                    "stat": 0.00013031184844690652,
                    "syst": 0.00018545690625906838,
                    "tagIso": 3.8825684985810405e-05,
                    "value": 0.9990074140906974
                }
            },
            "abseta:[0.9,1.2]": {
                "pt:[15,20]": {
                    "AltSig": 0.0008000972256207994,
                    "massBin": 0.0003056917675766102,
                    "massRange": 0.0003071559982253391,
                    "stat": 0.0007597376852510366,
                    "syst": 0.0009123602151532175,
                    "tagIso": 6.673325811323849e-05,
                    "value": 0.996259901420793
                },
                "pt:[20,25]": {
                    "AltSig": 0.00010867335741160389,
                    "massBin": 0.0003475828107922241,
                    "massRange": 0.00019780446565231813,
                    "stat": 0.0003964606181266464,
                    "syst": 0.0004264529337112849,
                    "tagIso": 0.00010055739191938695,
                    "value": 0.9976350417508058
                },
                "pt:[25,30]": {
                    "AltSig": 0.001142114236780345,
                    "massBin": 0.0005016260623313396,
                    "massRange": 0.00022214988051177942,
                    "stat": 0.00023676656166895317,
                    "syst": 0.0012827779023957763,
                    "tagIso": 0.00020028714685949023,
                    "value": 0.9986466106007387
                },
                "pt:[30,40]": {
                    "AltSig": 1.5761108404399593e-05,
                    "massBin": 3.467699246323397e-05,
                    "massRange": 6.469847628631786e-05,
                    "stat": 0.00010099905300688346,
                    "syst": 7.798439741994094e-05,
                    "tagIso": 2.108950124468656e-05,
                    "value": 0.9975693595763792
                },
                "pt:[40,50]": {
                    "AltSig": 1.633252975430377e-05,
                    "massBin": 7.16503096026555e-06,
                    "massRange": 1.914101610472896e-05,
                    "stat": 8.428751085181169e-05,
                    "syst": 2.912146154131604e-05,
                    "tagIso": 1.279030210526999e-05,
                    "value": 0.997836013711497
                },
                "pt:[50,60]": {
                    "AltSig": 8.061810785153778e-05,
                    "massBin": 0.00020029962524931166,
                    "massRange": 1.7863294502817872e-05,
                    "stat": 0.00016938692801294995,
                    "syst": 0.00022111974781512022,
                    "tagIso": 4.4222464819942964e-05,
                    "value": 0.9979937527254581
                },
                "pt:[60,120]": {
                    "AltSig": 0.00019120446965104065,
                    "massBin": 0.0002097233806032106,
                    "massRange": 1.183568634877119e-05,
                    "stat": 0.00025702307913268917,
                    "syst": 0.0003262246521603114,
                    "tagIso": 0.00016043501681239913,
                    "value": 0.9974837908600083
                }
            },
            "abseta:[1.2,2.1]": {
                "pt:[15,20]": {
                    "AltSig": 0.0006302212291710019,
                    "massBin": 0.00016594797542729411,
                    "massRange": 7.417665242320792e-05,
                    "stat": 0.00027718897912844075,
                    "syst": 0.0006859974970020848,
                    "tagIso": 0.000200929992490384,
                    "value": 0.998169222364488
                },
                "pt:[20,25]": {
                    "AltSig": 0.0003060332183281167,
                    "massBin": 2.4492120633323733e-05,
                    "massRange": 0.00011962814801291799,
                    "stat": 0.0002324431183143172,
                    "syst": 0.0003328066207716982,
                    "tagIso": 4.683116845749513e-05,
                    "value": 0.9982901624835293
                },
                "pt:[25,30]": {
                    "AltSig": 0.00018481716329465936,
                    "massBin": 7.400588886402604e-05,
                    "massRange": 4.140287112497365e-05,
                    "stat": 0.00012906414878134314,
                    "syst": 0.0002206940290553481,
                    "tagIso": 8.577529532710626e-05,
                    "value": 0.9988849025479501
                },
                "pt:[30,40]": {
                    "AltSig": 6.856047857140002e-05,
                    "massBin": 1.232832969172426e-05,
                    "massRange": 8.145675895465665e-06,
                    "stat": 5.103358467815532e-05,
                    "syst": 7.06223215539624e-05,
                    "tagIso": 8.28452358014875e-06,
                    "value": 0.9989169146696069
                },
                "pt:[40,50]": {
                    "AltSig": 4.372139720987267e-05,
                    "massBin": 9.433046216034136e-06,
                    "massRange": 1.6070095931519646e-05,
                    "stat": 4.017902144242365e-05,
                    "syst": 4.9331164197623094e-05,
                    "tagIso": 1.3220168037786362e-05,
                    "value": 0.9991740154112545
                },
                "pt:[50,60]": {
                    "AltSig": 0.00010270340969842362,
                    "massBin": 0.00027344559338343677,
                    "massRange": 4.725519012077628e-05,
                    "stat": 8.962486956604772e-05,
                    "syst": 0.0002971876518725445,
                    "tagIso": 2.769412442493735e-05,
                    "value": 0.9990859637135794
                },
                "pt:[60,120]": {
                    "AltSig": 0.00015345188978632684,
                    "massBin": 8.377360212541429e-05,
                    "massRange": 7.751902399294464e-05,
                    "stat": 0.00016002897380811652,
                    "syst": 0.00019873227077703864,
                    "tagIso": 5.4035335432633946e-05,
                    "value": 0.9991671729713645
                }
            },
            "abseta:[2.1,2.4]": {
                "pt:[15,20]": {
                    "AltSig": 0.004514233185265448,
                    "massBin": 0.00011850029618465374,
                    "massRange": 0.001550991230769072,
                    "stat": 0.0011526874003740344,
                    "syst": 0.004806305084530271,
                    "tagIso": 0.0005501374342028464,
                    "value": 0.9899696246376983
                },
                "pt:[20,25]": {
                    "AltSig": 0.0006818448192098536,
                    "massBin": 0.0003703609877234171,
                    "massRange": 0.00037596713171855756,
                    "stat": 0.0007368326118744958,
                    "syst": 0.001027023275970358,
                    "tagIso": 0.0005579837869879589,
                    "value": 0.9926275846855587
                },
                "pt:[25,30]": {
                    "AltSig": 0.00036296312295580613,
                    "massBin": 7.577653160395492e-05,
                    "massRange": 0.00019477928812511314,
                    "stat": 0.00045069467446903126,
                    "syst": 0.0004206777380013244,
                    "tagIso": 3.932526922512114e-05,
                    "value": 0.9941470348796974
                },
                "pt:[30,40]": {
                    "AltSig": 7.688390419846591e-05,
                    "massBin": 7.160106717224446e-05,
                    "massRange": 8.138315029254661e-05,
                    "stat": 0.0002084612728549371,
                    "syst": 0.00014764145769419868,
                    "tagIso": 6.431901222442304e-05,
                    "value": 0.9948129786848503
                },
                "pt:[40,50]": {
                    "AltSig": 0.0003520537652026423,
                    "massBin": 3.4986992149987906e-05,
                    "massRange": 4.863747446592903e-05,
                    "stat": 0.00020283894989895534,
                    "syst": 0.0003599542725087183,
                    "tagIso": 4.511686116959179e-05,
                    "value": 0.9953702145582024
                },
                "pt:[50,60]": {
                    "AltSig": 0.0005997198125921033,
                    "massBin": 0.00014277608663215702,
                    "massRange": 0.00011332698919680473,
                    "stat": 0.00043871323759347503,
                    "syst": 0.0006584457010510424,
                    "tagIso": 0.0002016404478835665,
                    "value": 0.9949683332302579
                },
                "pt:[60,120]": {
                    "AltSig": 0.0011327947502102198,
                    "massBin": 0.0004473102801562101,
                    "massRange": 0.00040781639696274574,
                    "stat": 0.0008332703805441096,
                    "syst": 0.0012955999619737168,
                    "tagIso": 0.0001701605565263553,
                    "value": 0.9950154991379151
                }
            }
        }
    },
    "NUM_MediumID_DEN_TrackerMuons": {
        "abseta_pt": {
            "abseta:[0.0,0.9]": {
                "pt:[15,20]": {
                    "AltSig": 0.00027471575573256857,
                    "massBin": 5.5069474850899525e-05,
                    "massRange": 0.0001715971545751538,
                    "stat": 0.0008601786708139706,
                    "syst": 0.000564420666991439,
                    "tagIso": 0.00045893759092136,
                    "value": 1.0000041738158354
                },
                "pt:[20,25]": {
                    "AltSig": 0.00033327503004598746,
                    "massBin": 0.00028706878956336057,
                    "massRange": 0.0001564528019862288,
                    "stat": 0.0003959876800880096,
                    "syst": 0.0004720832745583648,
                    "tagIso": 7.003144490069779e-05,
                    "value": 0.9990199540731494
                },
                "pt:[25,30]": {
                    "AltSig": 0.00016302027210368664,
                    "massBin": 5.393212902204958e-05,
                    "massRange": 5.008071671580572e-05,
                    "stat": 0.00022773718625988576,
                    "syst": 0.00020957269031497458,
                    "tagIso": 0.00010921698897825571,
                    "value": 0.999548660646305
                },
                "pt:[30,40]": {
                    "AltSig": 4.874011485744845e-05,
                    "massBin": 4.550136797643045e-05,
                    "massRange": 3.0453563486021462e-05,
                    "stat": 9.882877056076345e-05,
                    "syst": 8.826321816901563e-05,
                    "tagIso": 4.916302338658918e-05,
                    "value": 0.9992690049961371
                },
                "pt:[40,50]": {
                    "AltSig": 0.00011278764208733083,
                    "massBin": 1.988857658069554e-05,
                    "massRange": 6.389118940580696e-05,
                    "stat": 8.737557331369838e-05,
                    "syst": 0.00020486711074607213,
                    "tagIso": 0.00015739072811232768,
                    "value": 0.9992537131247722
                },
                "pt:[50,60]": {
                    "AltSig": 0.0005791489498547797,
                    "massBin": 0.00012591369425057897,
                    "massRange": 5.608513101473811e-05,
                    "stat": 0.00019317437505789973,
                    "syst": 0.0006074225462913447,
                    "tagIso": 0.00012061858606532416,
                    "value": 0.9987772239305885
                },
                "pt:[60,120]": {
                    "AltSig": 0.0005404862278002298,
                    "massBin": 8.561379550059423e-05,
                    "massRange": 5.5682022566116984e-05,
                    "stat": 0.00031784697051686934,
                    "syst": 0.0005532991463596898,
                    "tagIso": 5.98696359064288e-05,
                    "value": 0.9988329307945766
                }
            },
            "abseta:[0.9,1.2]": {
                "pt:[15,20]": {
                    "AltSig": 0.0015047222278958827,
                    "massBin": 0.00017086908213453933,
                    "massRange": 6.694572776744234e-05,
                    "stat": 0.0010045775718316731,
                    "syst": 0.0015175989159814938,
                    "tagIso": 7.238448016283483e-05,
                    "value": 0.9935125772523964
                },
                "pt:[20,25]": {
                    "AltSig": 0.00019307456410511126,
                    "massBin": 0.0001900368839583555,
                    "massRange": 0.0002481980060077271,
                    "stat": 0.000624055540658187,
                    "syst": 0.0003810818551440267,
                    "tagIso": 0.00010114012836071051,
                    "value": 0.9945582990388511
                },
                "pt:[25,30]": {
                    "AltSig": 0.0005922162371457818,
                    "massBin": 0.0004827848562918846,
                    "massRange": 0.00023287561704304904,
                    "stat": 0.0003850149576596849,
                    "syst": 0.0008325619017976896,
                    "tagIso": 0.00023479135058157574,
                    "value": 0.9963131040992652
                },
                "pt:[30,40]": {
                    "AltSig": 3.417991958321043e-05,
                    "massBin": 8.634764039650022e-05,
                    "massRange": 7.731436221825039e-05,
                    "stat": 0.00017367310916452855,
                    "syst": 0.0001283921408246135,
                    "tagIso": 4.339181161872041e-05,
                    "value": 0.995557465152997
                },
                "pt:[40,50]": {
                    "AltSig": 0.0001065862436934184,
                    "massBin": 1.4465763786053465e-05,
                    "massRange": 1.6132045603023393e-05,
                    "stat": 9.94173923380796e-05,
                    "syst": 0.00011231231023794837,
                    "tagIso": 2.799868691671925e-05,
                    "value": 0.995849044136711
                },
                "pt:[50,60]": {
                    "AltSig": 0.0005129407392913121,
                    "massBin": 0.0003062117264373554,
                    "massRange": 8.645669719731242e-05,
                    "stat": 0.0003227961196216425,
                    "syst": 0.0006104610369221816,
                    "tagIso": 9.118165208732432e-05,
                    "value": 0.9960145401876055
                },
                "pt:[60,120]": {
                    "AltSig": 6.316016464036345e-05,
                    "massBin": 0.00030465532410522966,
                    "massRange": 0.00029912793916747615,
                    "stat": 0.0005084805877852895,
                    "syst": 0.000487557180895765,
                    "tagIso": 0.00022678273247622727,
                    "value": 0.9955682146213594
                }
            },
            "abseta:[1.2,2.1]": {
                "pt:[15,20]": {
                    "AltSig": 0.0005289824599382653,
                    "massBin": 0.00021636678675590604,
                    "massRange": 0.000397639241289216,
                    "stat": 0.0005685359587330408,
                    "syst": 0.0006983311895402412,
                    "tagIso": 5.396716351829811e-05,
                    "value": 0.9952467407300474
                },
                "pt:[20,25]": {
                    "AltSig": 0.00044543539439745317,
                    "massBin": 8.325177558016206e-05,
                    "massRange": 0.00012549117712484792,
                    "stat": 0.0003356874303065063,
                    "syst": 0.0004740859180006517,
                    "tagIso": 6.05464564700231e-05,
                    "value": 0.9956863884750183
                },
                "pt:[25,30]": {
                    "AltSig": 0.0002730757124530525,
                    "massBin": 0.00014478377964738387,
                    "massRange": 9.641838443252837e-05,
                    "stat": 0.0002161805712513824,
                    "syst": 0.00032761061763243764,
                    "tagIso": 4.999524325577376e-05,
                    "value": 0.9963280270258894
                },
                "pt:[30,40]": {
                    "AltSig": 0.00024240885831872117,
                    "massBin": 2.263147318731784e-05,
                    "massRange": 2.6376478841405593e-05,
                    "stat": 0.00010652226458738498,
                    "syst": 0.00024776317741013847,
                    "tagIso": 3.763821560970326e-05,
                    "value": 0.9963540789044505
                },
                "pt:[40,50]": {
                    "AltSig": 0.00012355037705091831,
                    "massBin": 5.634722460845509e-06,
                    "massRange": 4.571345143145056e-06,
                    "stat": 9.237787689623623e-05,
                    "syst": 0.0001289401576951923,
                    "tagIso": 3.6169342037262187e-05,
                    "value": 0.997101761840005
                },
                "pt:[50,60]": {
                    "AltSig": 0.0007493045450368552,
                    "massBin": 0.00013575145676236744,
                    "massRange": 4.3332023879572024e-05,
                    "stat": 0.00019318278267972295,
                    "syst": 0.0007628940837254215,
                    "tagIso": 1.5619201764405233e-05,
                    "value": 0.9967922838866176
                },
                "pt:[60,120]": {
                    "AltSig": 0.0009742340477336686,
                    "massBin": 5.432423482343296e-05,
                    "massRange": 6.149514755016128e-05,
                    "stat": 0.00030088895858199717,
                    "syst": 0.0009800654473114906,
                    "tagIso": 6.829001090186138e-05,
                    "value": 0.9967515371285344
                }
            },
            "abseta:[2.1,2.4]": {
                "pt:[15,20]": {
                    "AltSig": 0.002296747626467144,
                    "massBin": 0.0006526142453027184,
                    "massRange": 0.0004448559209583869,
                    "stat": 0.0016951827055367084,
                    "syst": 0.0025267737576253405,
                    "tagIso": 0.0006969460660322668,
                    "value": 0.9785830351419386
                },
                "pt:[20,25]": {
                    "AltSig": 0.0017984042410587042,
                    "massBin": 0.0007944679891845885,
                    "massRange": 0.0003718940415339267,
                    "stat": 0.000932374216939853,
                    "syst": 0.0022249356957739557,
                    "tagIso": 0.0009729318948948906,
                    "value": 0.9768825062950853
                },
                "pt:[25,30]": {
                    "AltSig": 0.0016648899394210437,
                    "massBin": 9.145009549127447e-05,
                    "massRange": 0.0006120410900375961,
                    "stat": 0.0008311682336556818,
                    "syst": 0.0017829319310747052,
                    "tagIso": 0.0001550172396883598,
                    "value": 0.9771488876540625
                },
                "pt:[30,40]": {
                    "AltSig": 0.00037955389535970774,
                    "massBin": 7.519919746040715e-05,
                    "massRange": 0.0001745876120555767,
                    "stat": 0.00032576920173523545,
                    "syst": 0.0004452209055642609,
                    "tagIso": 0.00013425625380880657,
                    "value": 0.9785912698952179
                },
                "pt:[40,50]": {
                    "AltSig": 0.0011421418555527252,
                    "massBin": 3.401884792814114e-05,
                    "massRange": 6.520104948770644e-05,
                    "stat": 0.0004903094543542754,
                    "syst": 0.0011478870579998048,
                    "tagIso": 8.802397883173052e-05,
                    "value": 0.9775049786244718
                },
                "pt:[50,60]": {
                    "AltSig": 0.002916835575515364,
                    "massBin": 5.008143053525371e-05,
                    "massRange": 0.00022362592691393957,
                    "stat": 0.0010103949010114184,
                    "syst": 0.0029269772461217904,
                    "tagIso": 8.215424426089024e-05,
                    "value": 0.978501128153901
                },
                "pt:[60,120]": {
                    "AltSig": 0.005297713457707354,
                    "massBin": 0.00010239515395776833,
                    "massRange": 0.0005638061569860908,
                    "stat": 0.0013043174499750459,
                    "syst": 0.005423134349654305,
                    "tagIso": 0.0010080953051261332,
                    "value": 0.9759579114670028
                }
            }
        }
    },
    "NUM_MediumPromptID_DEN_TrackerMuons": {
        "abseta_pt": {
            "abseta:[0.0,0.9]": {
                "pt:[15,20]": {
                    "AltSig": 0.00015092164299213007,
                    "massBin": 0.00015604453709838761,
                    "massRange": 0.0001812089677205031,
                    "stat": 0.0010332790720659465,
                    "syst": 0.004891512880059627,
                    "tagIso": 0.004883332297307363,
                    "value": 0.9989946454440711
                },
                "pt:[20,25]": {
                    "AltSig": 0.0004039553072783253,
                    "massBin": 0.00036155372501156524,
                    "massRange": 0.0003450879304963128,
                    "stat": 0.00046546645549764437,
                    "syst": 0.0029590692326126405,
                    "tagIso": 0.0028884431892063356,
                    "value": 0.9978545311774981
                },
                "pt:[25,30]": {
                    "AltSig": 0.0003486519932630605,
                    "massBin": 0.0002345557042405244,
                    "massRange": 0.00017220202024298414,
                    "stat": 0.00026169050617219126,
                    "syst": 0.0028618303877307534,
                    "tagIso": 0.002825569861384658,
                    "value": 0.997913388821922
                },
                "pt:[30,40]": {
                    "AltSig": 0.0001234689134093081,
                    "massBin": 4.1491324721698586e-05,
                    "massRange": 6.161814962973855e-05,
                    "stat": 9.215847696410709e-05,
                    "syst": 0.0032413716801060616,
                    "tagIso": 0.0032381673010553613,
                    "value": 0.997675174375399
                },
                "pt:[40,50]": {
                    "AltSig": 0.00016047900756310796,
                    "massBin": 1.7862961432690838e-05,
                    "massRange": 0.00010065760971394999,
                    "stat": 9.407726358819413e-05,
                    "syst": 0.003126434702994962,
                    "tagIso": 0.003120639261503688,
                    "value": 0.997776511113738
                },
                "pt:[50,60]": {
                    "AltSig": 0.0009932825987970517,
                    "massBin": 0.00021326035556495926,
                    "massRange": 9.131533484729726e-05,
                    "stat": 0.00020652262464748827,
                    "syst": 0.0031437130049792434,
                    "tagIso": 0.002973634588675722,
                    "value": 0.9974603539052378
                },
                "pt:[60,120]": {
                    "AltSig": 0.000798990227023344,
                    "massBin": 2.224076962348276e-05,
                    "massRange": 6.099927457536847e-05,
                    "stat": 0.0003353221258108907,
                    "syst": 0.0026152576215651467,
                    "tagIso": 0.0024893717040537777,
                    "value": 0.9975464546902968
                }
            },
            "abseta:[0.9,1.2]": {
                "pt:[15,20]": {
                    "AltSig": 0.0025221176598412276,
                    "massBin": 0.0008568203929592566,
                    "massRange": 0.00043826147053321884,
                    "stat": 0.0012813260242816975,
                    "syst": 0.005696110887618913,
                    "tagIso": 0.005015813737732189,
                    "value": 0.9919842265046085
                },
                "pt:[20,25]": {
                    "AltSig": 0.0007821305098193454,
                    "massBin": 0.0003769580011508955,
                    "massRange": 0.00039125863162325913,
                    "stat": 0.0007090006982070787,
                    "syst": 0.005209121304985929,
                    "tagIso": 0.005121331465958501,
                    "value": 0.9919130987554542
                },
                "pt:[25,30]": {
                    "AltSig": 0.0003940953396828206,
                    "massBin": 0.0006913029062246556,
                    "massRange": 0.00022986214741016475,
                    "stat": 0.000433289109158587,
                    "syst": 0.004213480698501365,
                    "tagIso": 0.004131267619619572,
                    "value": 0.9946453047855335
                },
                "pt:[30,40]": {
                    "AltSig": 0.00037258977785636915,
                    "massBin": 0.00010056052410389871,
                    "massRange": 9.327190557123499e-05,
                    "stat": 0.00019456749915479067,
                    "syst": 0.003570841418788545,
                    "tagIso": 0.0035487002167266524,
                    "value": 0.9942698388235144
                },
                "pt:[40,50]": {
                    "AltSig": 0.0001331596535937285,
                    "massBin": 7.230329619201115e-05,
                    "massRange": 4.41327392192159e-05,
                    "stat": 0.00016368157903162256,
                    "syst": 0.003314678702372504,
                    "tagIso": 0.0033109195008796943,
                    "value": 0.9946767180321772
                },
                "pt:[50,60]": {
                    "AltSig": 0.0010387305363371846,
                    "massBin": 0.0005045753912845674,
                    "massRange": 0.00017211379524995074,
                    "stat": 0.00034650509590961547,
                    "syst": 0.003215088685769444,
                    "tagIso": 0.002995599213218958,
                    "value": 0.9947120994489058
                },
                "pt:[60,120]": {
                    "AltSig": 0.0006888685298418462,
                    "massBin": 0.0005376297148842468,
                    "massRange": 0.00015490965412778834,
                    "stat": 0.000536420797347926,
                    "syst": 0.002006039220611731,
                    "tagIso": 0.001799058306992174,
                    "value": 0.9941142046831292
                }
            },
            "abseta:[1.2,2.1]": {
                "pt:[15,20]": {
                    "AltSig": 0.0021367311170962244,
                    "massBin": 0.00030673010029164116,
                    "massRange": 0.00032936300577895983,
                    "stat": 0.000688684178721738,
                    "syst": 0.005632897035647641,
                    "tagIso": 0.005192431588710633,
                    "value": 0.9918074829281192
                },
                "pt:[20,25]": {
                    "AltSig": 0.0013716038294778743,
                    "massBin": 7.361305700598342e-05,
                    "massRange": 0.00014060053325237742,
                    "stat": 0.00039978790495508366,
                    "syst": 0.004147846054840859,
                    "tagIso": 0.003911283988348058,
                    "value": 0.992717505993486
                },
                "pt:[25,30]": {
                    "AltSig": 0.0005378079623156173,
                    "massBin": 0.0002497706227612695,
                    "massRange": 0.00019170145315416942,
                    "stat": 0.0002603503089843982,
                    "syst": 0.0044170303688398065,
                    "tagIso": 0.004372846334344149,
                    "value": 0.9937778499373136
                },
                "pt:[30,40]": {
                    "AltSig": 0.0005463407826362676,
                    "massBin": 0.0002716767729366576,
                    "massRange": 1.9638956116285744e-05,
                    "stat": 0.00012864875379184186,
                    "syst": 0.004138473926939391,
                    "tagIso": 0.004093199755159149,
                    "value": 0.9943992613086199
                },
                "pt:[40,50]": {
                    "AltSig": 0.00030133278373856154,
                    "massBin": 4.768404782418134e-06,
                    "massRange": 2.7695794018067765e-05,
                    "stat": 0.00011170871840601257,
                    "syst": 0.0031689420882346324,
                    "tagIso": 0.0031544575947916598,
                    "value": 0.9957558865828395
                },
                "pt:[50,60]": {
                    "AltSig": 0.0021877987563700962,
                    "massBin": 0.000384033253514271,
                    "massRange": 6.781833131414006e-05,
                    "stat": 0.0002301975585506283,
                    "syst": 0.0037871929360825235,
                    "tagIso": 0.003066640844779811,
                    "value": 0.9948030454066371
                },
                "pt:[60,120]": {
                    "AltSig": 0.002667890011126439,
                    "massBin": 0.00019712943845612285,
                    "massRange": 0.0004170597650716701,
                    "stat": 0.0003560729286034929,
                    "syst": 0.0040609823029434606,
                    "tagIso": 0.0030267377306605336,
                    "value": 0.9948878287501622
                }
            },
            "abseta:[2.1,2.4]": {
                "pt:[15,20]": {
                    "AltSig": 0.0021087926973708537,
                    "massBin": 0.0009165855838342285,
                    "massRange": 0.0005540996583014435,
                    "stat": 0.0019107162809229366,
                    "syst": 0.007095502644311807,
                    "tagIso": 0.006689693234456173,
                    "value": 0.9740205713137887
                },
                "pt:[20,25]": {
                    "AltSig": 0.003726309963304142,
                    "massBin": 0.0005912680361736533,
                    "massRange": 0.0006447462054347541,
                    "stat": 0.0016022434723233113,
                    "syst": 0.006124839385822922,
                    "tagIso": 0.0047815244430500226,
                    "value": 0.9762874950826814
                },
                "pt:[25,30]": {
                    "AltSig": 0.0037490700080877737,
                    "massBin": 5.688273249826459e-05,
                    "massRange": 0.0007837264118955578,
                    "stat": 0.001155339331397968,
                    "syst": 0.006495080486113297,
                    "tagIso": 0.005245291399110952,
                    "value": 0.9713757393499141
                },
                "pt:[30,40]": {
                    "AltSig": 0.002887565068877773,
                    "massBin": 6.0882688404761964e-05,
                    "massRange": 0.00024031839664245824,
                    "stat": 0.0006083883556240386,
                    "syst": 0.005109452897051179,
                    "tagIso": 0.0042079706803481165,
                    "value": 0.9753961514704668
                },
                "pt:[40,50]": {
                    "AltSig": 0.004003854920546113,
                    "massBin": 0.00021440986767906622,
                    "massRange": 0.00019543995558396476,
                    "stat": 0.0006486599509830999,
                    "syst": 0.0051779806293772565,
                    "tagIso": 0.00327054442040281,
                    "value": 0.9760821505255115
                },
                "pt:[50,60]": {
                    "AltSig": 0.010857943517002644,
                    "massBin": 7.446291381724146e-05,
                    "massRange": 0.0006074272233739797,
                    "stat": 0.0013566954455251643,
                    "syst": 0.011264440495435934,
                    "tagIso": 0.0029356719332321868,
                    "value": 0.9763105985363022
                },
                "pt:[60,120]": {
                    "AltSig": 0.02079329925733997,
                    "massBin": 0.00029639035687839543,
                    "massRange": 0.0018080316938001162,
                    "stat": 0.0022289795320676103,
                    "syst": 0.02157956153811837,
                    "tagIso": 0.005473514074404717,
                    "value": 0.9675147154100618
                }
            }
        }
    },
    "NUM_SoftID_DEN_TrackerMuons": {
        "abseta_pt": {
            "abseta:[0.0,0.9]": {
                "pt:[15,20]": {
                    "AltSig": 0.0002094956003608761,
                    "massBin": 4.465675621700971e-05,
                    "massRange": 1.5542555095726662e-05,
                    "stat": 0.0006878920025825504,
                    "syst": 0.0002535459614296197,
                    "tagIso": 0.00013476405712198325,
                    "value": 1.0023903164168588
                },
                "pt:[20,25]": {
                    "AltSig": 0.00034237420813187924,
                    "massBin": 6.061255656519826e-05,
                    "massRange": 4.6486956641444976e-05,
                    "stat": 0.00035978658013426795,
                    "syst": 0.00035699064870732647,
                    "tagIso": 6.623673995143076e-05,
                    "value": 1.000765684274606
                },
                "pt:[25,30]": {
                    "AltSig": 3.143308552622237e-05,
                    "massBin": 9.349748688614046e-05,
                    "massRange": 8.869240849862514e-06,
                    "stat": 0.00022031906651897104,
                    "syst": 0.00014359633432384762,
                    "tagIso": 0.00010397800189593243,
                    "value": 1.000143438305596
                },
                "pt:[30,40]": {
                    "AltSig": 0.00010290987722283429,
                    "massBin": 4.082664278148851e-05,
                    "massRange": 7.206202596177214e-05,
                    "stat": 0.00010107377411232413,
                    "syst": 0.00013711415513899887,
                    "tagIso": 3.67436846674396e-05,
                    "value": 0.9994521384346335
                },
                "pt:[40,50]": {
                    "AltSig": 7.721113387459955e-05,
                    "massBin": 2.3952582965947045e-05,
                    "massRange": 1.5739258992897298e-05,
                    "stat": 7.670078021248455e-05,
                    "syst": 0.00011371619283079692,
                    "tagIso": 7.841149669113312e-05,
                    "value": 0.9985724802901265
                },
                "pt:[50,60]": {
                    "AltSig": 0.0007290558071383346,
                    "massBin": 0.0002250212972012,
                    "massRange": 5.2100414657085814e-05,
                    "stat": 0.0002022519603514231,
                    "syst": 0.0007684163925616997,
                    "tagIso": 7.47819833506469e-05,
                    "value": 0.9981978966500833
                },
                "pt:[60,120]": {
                    "AltSig": 0.0004819783757286089,
                    "massBin": 0.0002146659294569031,
                    "massRange": 2.27172437580192e-05,
                    "stat": 0.0003186745416755153,
                    "syst": 0.0005316664846644442,
                    "tagIso": 6.138861304755272e-05,
                    "value": 0.997423856513715
                }
            },
            "abseta:[0.9,1.2]": {
                "pt:[15,20]": {
                    "AltSig": 2.4540033568998254e-05,
                    "massBin": 3.331880254364705e-05,
                    "massRange": 0.00022382634512030375,
                    "stat": 0.0009335048271883569,
                    "syst": 0.0008785885878268988,
                    "tagIso": 0.0008485913728286665,
                    "value": 1.0085892971722528
                },
                "pt:[20,25]": {
                    "AltSig": 4.5995418438860014e-05,
                    "massBin": 0.0001005929849600129,
                    "massRange": 6.913392672314167e-05,
                    "stat": 0.0005423565120114088,
                    "syst": 0.00021163469349908722,
                    "tagIso": 0.0001666589827394871,
                    "value": 1.0068265730899826
                },
                "pt:[25,30]": {
                    "AltSig": 0.00018050333418262454,
                    "massBin": 3.638514525017289e-05,
                    "massRange": 0.00012191737832423222,
                    "stat": 0.0003810347279395527,
                    "syst": 0.0002382757786750736,
                    "tagIso": 8.947718770635493e-05,
                    "value": 1.0075260613718167
                },
                "pt:[30,40]": {
                    "AltSig": 1.3481089769395993e-05,
                    "massBin": 6.788594493944977e-05,
                    "massRange": 0.00011974156493232968,
                    "stat": 0.0001753230492051223,
                    "syst": 0.00015922700792601405,
                    "tagIso": 7.889839275254662e-05,
                    "value": 1.0074218701997995
                },
                "pt:[40,50]": {
                    "AltSig": 1.1744520435730266e-05,
                    "massBin": 3.835923039097189e-06,
                    "massRange": 6.978188169859401e-06,
                    "stat": 0.00015308773797360371,
                    "syst": 5.5857908854641974e-05,
                    "tagIso": 5.402557547729003e-05,
                    "value": 1.0072568538413667
                },
                "pt:[50,60]": {
                    "AltSig": 0.00013539157843767136,
                    "massBin": 0.00024057973521174336,
                    "massRange": 0.00024970487040931744,
                    "stat": 0.00033207457944782183,
                    "syst": 0.0003877000728905944,
                    "tagIso": 0.00010839435274423437,
                    "value": 1.0068793383635948
                },
                "pt:[60,120]": {
                    "AltSig": 5.484691437307454e-05,
                    "massBin": 0.00020001226318078213,
                    "massRange": 0.0001623852716234886,
                    "stat": 0.0005153134260893321,
                    "syst": 0.0002963200256658134,
                    "tagIso": 0.00013573316371251476,
                    "value": 1.006405640981863
                }
            },
            "abseta:[1.2,2.1]": {
                "pt:[15,20]": {
                    "AltSig": 0.0001273462818791593,
                    "massBin": 0.0002196067070791008,
                    "massRange": 0.0003996015526244734,
                    "stat": 0.0004521042738931852,
                    "syst": 0.000490706238311775,
                    "tagIso": 0.0001291008526526083,
                    "value": 0.9992123750897944
                },
                "pt:[20,25]": {
                    "AltSig": 0.00022083276823525733,
                    "massBin": 0.00021128922660873517,
                    "massRange": 8.206885162215238e-05,
                    "stat": 0.0002482326081949632,
                    "syst": 0.0003288778315324432,
                    "tagIso": 8.95269951441402e-05,
                    "value": 0.9985957450311477
                },
                "pt:[25,30]": {
                    "AltSig": 0.00011587915475863575,
                    "massBin": 0.00017626767735545723,
                    "massRange": 6.076143036043424e-05,
                    "stat": 0.00015950588551461267,
                    "syst": 0.0002520698309921429,
                    "tagIso": 0.00012389098308229762,
                    "value": 0.9986525311574269
                },
                "pt:[30,40]": {
                    "AltSig": 1.0549243230073557e-06,
                    "massBin": 7.332991770286901e-05,
                    "massRange": 2.34699597296828e-05,
                    "stat": 7.790351730978735e-05,
                    "syst": 8.573028289203913e-05,
                    "tagIso": 3.7688893581522276e-05,
                    "value": 0.998887494143488
                },
                "pt:[40,50]": {
                    "AltSig": 0.00012391083962415284,
                    "massBin": 2.931686465512673e-05,
                    "massRange": 1.4446627527808786e-05,
                    "stat": 6.892345327191712e-05,
                    "syst": 0.00015012127390415865,
                    "tagIso": 7.819409889570084e-05,
                    "value": 0.9992585462265264
                },
                "pt:[50,60]": {
                    "AltSig": 0.0005290312171489786,
                    "massBin": 0.00010610142105238474,
                    "massRange": 3.097457158324213e-05,
                    "stat": 0.00015492259634954938,
                    "syst": 0.0005512347505444168,
                    "tagIso": 0.00010848403502605741,
                    "value": 0.9995425287833225
                },
                "pt:[60,120]": {
                    "AltSig": 0.00030734655032116365,
                    "massBin": 0.0001756270004971694,
                    "massRange": 3.886986894841016e-05,
                    "stat": 0.0002503369605427166,
                    "syst": 0.0006330051610801789,
                    "tagIso": 0.0005233334710718629,
                    "value": 0.9993612062670744
                }
            },
            "abseta:[2.1,2.4]": {
                "pt:[15,20]": {
                    "AltSig": 0.002271068730261616,
                    "massBin": 0.0004565983711944388,
                    "massRange": 0.0004329872979082494,
                    "stat": 0.0010170126582327702,
                    "syst": 0.0025286849311474745,
                    "tagIso": 0.0009168065394143388,
                    "value": 0.9980633942170023
                },
                "pt:[20,25]": {
                    "AltSig": 0.00012827456474218124,
                    "massBin": 0.0004945060420166736,
                    "massRange": 0.0004061823584606272,
                    "stat": 0.0005748492837339934,
                    "syst": 0.0007180766525392482,
                    "tagIso": 0.00029943176358987467,
                    "value": 0.9981823618002822
                },
                "pt:[25,30]": {
                    "AltSig": 0.0008777842369022126,
                    "massBin": 1.4462276385407424e-05,
                    "massRange": 0.00036623943362329436,
                    "stat": 0.0003567273108756581,
                    "syst": 0.0012597950930584507,
                    "tagIso": 0.0008259770152741486,
                    "value": 0.9988733190100902
                },
                "pt:[30,40]": {
                    "AltSig": 0.00035820508532147244,
                    "massBin": 1.3747267477881575e-05,
                    "massRange": 2.844682684238764e-05,
                    "stat": 0.00018011602746720708,
                    "syst": 0.0006622149723127542,
                    "tagIso": 0.0005560751541693887,
                    "value": 0.9987779043673699
                },
                "pt:[40,50]": {
                    "AltSig": 0.0005316825479489973,
                    "massBin": 3.52123369250501e-05,
                    "massRange": 0.0001752255576727424,
                    "stat": 0.00018886626361178316,
                    "syst": 0.0010214960711609057,
                    "tagIso": 0.0008537118875066585,
                    "value": 0.9993243386316059
                },
                "pt:[50,60]": {
                    "AltSig": 0.002457861353232893,
                    "massBin": 4.624590805307749e-05,
                    "massRange": 0.0003536597069001002,
                    "stat": 0.0005004425992520019,
                    "syst": 0.0027168164171745713,
                    "tagIso": 0.001101269785573511,
                    "value": 0.9991754986610206
                },
                "pt:[60,120]": {
                    "AltSig": 0.001975384370036304,
                    "massBin": 5.1168419597957815e-05,
                    "massRange": 0.00019028694437628335,
                    "stat": 0.0009620714534366956,
                    "syst": 0.0032077348203022756,
                    "tagIso": 0.0025196412323248984,
                    "value": 1.0009690343089361
                }
            }
        }
    },
    "NUM_TightID_DEN_TrackerMuons": {
        "abseta_pt": {
            "abseta:[0.0,0.9]": {
                "pt:[15,20]": {
                    "AltSig": 0.00035966727916836305,
                    "massBin": 0.00015868854195111304,
                    "massRange": 0.00017501177057077655,
                    "stat": 0.0013310345930684859,
                    "syst": 0.004632699705939745,
                    "tagIso": 0.004612671117749989,
                    "value": 0.989426853595162
                },
                "pt:[20,25]": {
                    "AltSig": 0.00044179096351737446,
                    "massBin": 0.00015103522022347216,
                    "massRange": 0.0004940952565677392,
                    "stat": 0.0006994812439310365,
                    "syst": 0.0030444394074334224,
                    "tagIso": 0.002967573131327561,
                    "value": 0.9876263789818742
                },
                "pt:[25,30]": {
                    "AltSig": 0.00018182489189644269,
                    "massBin": 0.0002834363400303075,
                    "massRange": 1.410343838625927e-05,
                    "stat": 0.0004364779456506582,
                    "syst": 0.0032032996398599495,
                    "tagIso": 0.0031855193023413997,
                    "value": 0.9879213364860953
                },
                "pt:[30,40]": {
                    "AltSig": 0.000130665163628918,
                    "massBin": 0.0002752872595606082,
                    "massRange": 9.859385534605192e-05,
                    "stat": 0.00019690273574954475,
                    "syst": 0.002979263788078298,
                    "tagIso": 0.0029619985669105398,
                    "value": 0.9864987155508051
                },
                "pt:[40,50]": {
                    "AltSig": 0.00011261487010449933,
                    "massBin": 5.486473282473314e-05,
                    "massRange": 0.00023899793928872093,
                    "stat": 0.00017624367492470627,
                    "syst": 0.0030936345005879015,
                    "tagIso": 0.0030818439545776677,
                    "value": 0.986725964237604
                },
                "pt:[50,60]": {
                    "AltSig": 0.0006139867585762682,
                    "massBin": 0.0004776439154914325,
                    "massRange": 0.0002948935188696322,
                    "stat": 0.00036800344692884684,
                    "syst": 0.003158292657484568,
                    "tagIso": 0.0030467567794519868,
                    "value": 0.9851702350485853
                },
                "pt:[60,120]": {
                    "AltSig": 0.0007310724460360962,
                    "massBin": 0.00032195700718135045,
                    "massRange": 0.0001766711672298582,
                    "stat": 0.0005716265142192276,
                    "syst": 0.0024322868944485544,
                    "tagIso": 0.002290564035286824,
                    "value": 0.9846264481111426
                }
            },
            "abseta:[0.9,1.2]": {
                "pt:[15,20]": {
                    "AltSig": 0.0013126035693741267,
                    "massBin": 0.0001415146817264068,
                    "massRange": 0.0003471911223333346,
                    "stat": 0.0016928485311664219,
                    "syst": 0.004796082123205046,
                    "tagIso": 0.0045977067676856165,
                    "value": 0.9789896702681764
                },
                "pt:[20,25]": {
                    "AltSig": 9.607644248732505e-05,
                    "massBin": 0.0007494829870997588,
                    "massRange": 0.0005366999650278648,
                    "stat": 0.0008132254609183925,
                    "syst": 0.00489229989205315,
                    "tagIso": 0.004803706480476233,
                    "value": 0.976582405610053
                },
                "pt:[25,30]": {
                    "AltSig": 0.001187019109801235,
                    "massBin": 0.0011563346602762037,
                    "massRange": 0.0003831750384131194,
                    "stat": 0.0007056772407261002,
                    "syst": 0.004687770139842223,
                    "tagIso": 0.0043683225110268675,
                    "value": 0.981508194670879
                },
                "pt:[30,40]": {
                    "AltSig": 0.0002151678611865826,
                    "massBin": 0.00038764127791601766,
                    "massRange": 0.00013677219021651643,
                    "stat": 0.00034321869789624254,
                    "syst": 0.0039612369765651915,
                    "tagIso": 0.003933971121355462,
                    "value": 0.9787189395312674
                },
                "pt:[40,50]": {
                    "AltSig": 0.0001528668863184368,
                    "massBin": 9.30982179387363e-05,
                    "massRange": 2.5815868061662695e-05,
                    "stat": 0.00026932522405685223,
                    "syst": 0.003234852704904341,
                    "tagIso": 0.0032297941111264494,
                    "value": 0.97924624137508
                },
                "pt:[50,60]": {
                    "AltSig": 0.0003276559180850347,
                    "massBin": 0.0007488780662740502,
                    "massRange": 0.00019879897019470238,
                    "stat": 0.0006426701488012385,
                    "syst": 0.002950176468953167,
                    "tagIso": 0.0028276922407878824,
                    "value": 0.9790338025922689
                },
                "pt:[60,120]": {
                    "AltSig": 0.0005606060511738065,
                    "massBin": 0.0011118450279942738,
                    "massRange": 0.0006861127667079359,
                    "stat": 0.0009894676247029868,
                    "syst": 0.0020799061156169685,
                    "tagIso": 0.001518150259445017,
                    "value": 0.9783224193724152
                }
            },
            "abseta:[1.2,2.1]": {
                "pt:[15,20]": {
                    "AltSig": 0.0007563961884078374,
                    "massBin": 0.0002857559222805839,
                    "massRange": 0.00038175387481820255,
                    "stat": 0.000650911896165961,
                    "syst": 0.005275069251901404,
                    "tagIso": 0.005198733302494041,
                    "value": 0.9901229250714404
                },
                "pt:[20,25]": {
                    "AltSig": 0.0006297131152557256,
                    "massBin": 0.0002786056440252649,
                    "massRange": 0.0002684998021760254,
                    "stat": 0.0004060591390853036,
                    "syst": 0.004119411251489946,
                    "tagIso": 0.004052566742538066,
                    "value": 0.9894478749401233
                },
                "pt:[25,30]": {
                    "AltSig": 0.0004824493481040415,
                    "massBin": 0.00015255364806920912,
                    "massRange": 3.331772272324729e-05,
                    "stat": 0.0002808878165206296,
                    "syst": 0.0043182324033032,
                    "tagIso": 0.004288355282537237,
                    "value": 0.9909722730656102
                },
                "pt:[30,40]": {
                    "AltSig": 0.0004446044784149894,
                    "massBin": 1.280203336639918e-05,
                    "massRange": 3.0134873938603146e-05,
                    "stat": 0.0001476503841859811,
                    "syst": 0.003917214296997478,
                    "tagIso": 0.0038917634439530335,
                    "value": 0.9905041240671784
                },
                "pt:[40,50]": {
                    "AltSig": 0.0002596926644407027,
                    "massBin": 2.2955405573343857e-05,
                    "massRange": 3.74052181896789e-05,
                    "stat": 0.0001357011962353961,
                    "syst": 0.0030560151870568817,
                    "tagIso": 0.0030446448795491965,
                    "value": 0.9915231885941245
                },
                "pt:[50,60]": {
                    "AltSig": 0.0015992874077050967,
                    "massBin": 0.0005190965331824393,
                    "massRange": 0.0001898297412233907,
                    "stat": 0.0002968003257486049,
                    "syst": 0.003001365008162464,
                    "tagIso": 0.0024789060406483765,
                    "value": 0.9906251149950824
                },
                "pt:[60,120]": {
                    "AltSig": 0.002207180804153719,
                    "massBin": 4.9018654006971474e-05,
                    "massRange": 0.00019212847528699006,
                    "stat": 0.0004825772141326968,
                    "syst": 0.003187644757869166,
                    "tagIso": 0.0022913131214850058,
                    "value": 0.9904946666670155
                }
            },
            "abseta:[2.1,2.4]": {
                "pt:[15,20]": {
                    "AltSig": 0.0034088422008616837,
                    "massBin": 0.0017980987967090023,
                    "massRange": 0.0007875639749199692,
                    "stat": 0.0017154273802081417,
                    "syst": 0.006810512984762477,
                    "tagIso": 0.005559628195115629,
                    "value": 0.975765140135644
                },
                "pt:[20,25]": {
                    "AltSig": 0.001989396815719635,
                    "massBin": 0.000650848516609237,
                    "massRange": 0.0009893772923516564,
                    "stat": 0.001204917684890574,
                    "syst": 0.005491977934938323,
                    "tagIso": 0.0049801255736437455,
                    "value": 0.9753059817018813
                },
                "pt:[25,30]": {
                    "AltSig": 0.002174145028776997,
                    "massBin": 5.853100582714488e-05,
                    "massRange": 0.00013209720305157324,
                    "stat": 0.0008558632044014962,
                    "syst": 0.005461722939767618,
                    "tagIso": 0.00500825671416022,
                    "value": 0.9761021473666666
                },
                "pt:[30,40]": {
                    "AltSig": 0.0013739891762528655,
                    "massBin": 5.76244786650304e-05,
                    "massRange": 0.00015500745179830577,
                    "stat": 0.00040062700919760033,
                    "syst": 0.004729327240566612,
                    "tagIso": 0.004522315999711979,
                    "value": 0.9759378668892583
                },
                "pt:[40,50]": {
                    "AltSig": 0.0022611056548738073,
                    "massBin": 5.644427793993767e-05,
                    "massRange": 0.00021333957369273904,
                    "stat": 0.0005430927408289706,
                    "syst": 0.004086572777828714,
                    "tagIso": 0.003396877765798001,
                    "value": 0.9764162471938509
                },
                "pt:[50,60]": {
                    "AltSig": 0.006485544067581839,
                    "massBin": 6.973992980030541e-05,
                    "massRange": 0.0003770164584676605,
                    "stat": 0.001168162081633446,
                    "syst": 0.007077148711119125,
                    "tagIso": 0.0028065542857719783,
                    "value": 0.9720100712920314
                },
                "pt:[60,120]": {
                    "AltSig": 0.009059937192714251,
                    "massBin": 0.0001953353262506563,
                    "massRange": 0.0008953734171460725,
                    "stat": 0.0020797108360396696,
                    "syst": 0.011779779966057445,
                    "tagIso": 0.007472677208804623,
                    "value": 0.9695502745497125
                }
            }
        }
    },
    "NUM_TrkHighPtID_DEN_TrackerMuons": {
        "abseta_pt": {
            "abseta:[0.0,0.9]": {
                "pt:[15,20]": {
                    "AltSig": 0.0004555375397942152,
                    "massBin": 0.00013251269230479812,
                    "massRange": 0.0001592484711678277,
                    "stat": 0.0011392373097462733,
                    "syst": 0.004290537615761745,
                    "tagIso": 0.004261253206852833,
                    "value": 0.994572915454412
                },
                "pt:[20,25]": {
                    "AltSig": 0.00038367177183451506,
                    "massBin": 0.0005475143080885259,
                    "massRange": 0.0005264927450816526,
                    "stat": 0.0005866308872204202,
                    "syst": 0.0038980698725478314,
                    "tagIso": 0.0038040476041418247,
                    "value": 0.9935897802442083
                },
                "pt:[25,30]": {
                    "AltSig": 0.00028057817040416655,
                    "massBin": 0.00018814114613968647,
                    "massRange": 0.00027742872123659446,
                    "stat": 0.0003600088823687742,
                    "syst": 0.0026663197192994506,
                    "tagIso": 0.0026302419944902455,
                    "value": 0.9921987696748443
                },
                "pt:[30,40]": {
                    "AltSig": 9.293220423178816e-05,
                    "massBin": 7.521265625748397e-05,
                    "massRange": 6.12972328508099e-05,
                    "stat": 0.0001597024955583519,
                    "syst": 0.0032183804061548765,
                    "tagIso": 0.0032155748708002085,
                    "value": 0.9918599916366647
                },
                "pt:[40,50]": {
                    "AltSig": 0.0001032416510009515,
                    "massBin": 3.527601263059177e-05,
                    "massRange": 0.0001489597546489585,
                    "stat": 0.0001417330900488558,
                    "syst": 0.0030898429652823365,
                    "tagIso": 0.0030843212066889447,
                    "value": 0.9921545380059331
                },
                "pt:[50,60]": {
                    "AltSig": 0.0009127042211216629,
                    "massBin": 0.0003367913374024978,
                    "massRange": 0.00017798554012282697,
                    "stat": 0.00029855020855130835,
                    "syst": 0.003279069082029836,
                    "tagIso": 0.0031263649486309997,
                    "value": 0.9912568273377299
                },
                "pt:[60,120]": {
                    "AltSig": 0.0006089409753571307,
                    "massBin": 0.0002715945708917089,
                    "massRange": 0.00010765949310992395,
                    "stat": 0.0004560674530408803,
                    "syst": 0.0023922797155246666,
                    "tagIso": 0.002294959465534707,
                    "value": 0.9914448267083757
                }
            },
            "abseta:[0.9,1.2]": {
                "pt:[15,20]": {
                    "AltSig": 0.0010680088678917121,
                    "massBin": 0.0007266697084927221,
                    "massRange": 0.0001398103284012686,
                    "stat": 0.0014053656639007083,
                    "syst": 0.005111556490886973,
                    "tagIso": 0.004943659679272516,
                    "value": 0.9883780566995524
                },
                "pt:[20,25]": {
                    "AltSig": 0.00016196885423447327,
                    "massBin": 0.00031764170768655564,
                    "massRange": 0.00023565006905251762,
                    "stat": 0.000832875466113994,
                    "syst": 0.004872630118533303,
                    "tagIso": 0.004853850343056465,
                    "value": 0.9861769628997428
                },
                "pt:[25,30]": {
                    "AltSig": 0.0011696436936889931,
                    "massBin": 0.0012053020059166752,
                    "massRange": 0.00028930500937895953,
                    "stat": 0.0005551804714199915,
                    "syst": 0.0050799969542049735,
                    "tagIso": 0.004785587985882911,
                    "value": 0.9899550786490829
                },
                "pt:[30,40]": {
                    "AltSig": 0.0006492417342224277,
                    "massBin": 0.00023933451899987856,
                    "massRange": 0.0004572834982164431,
                    "stat": 0.0001906677821685596,
                    "syst": 0.0034435692019087155,
                    "tagIso": 0.003342194609706639,
                    "value": 0.9878022549830155
                },
                "pt:[40,50]": {
                    "AltSig": 0.00013180085820985177,
                    "massBin": 0.00012463029771914158,
                    "massRange": 0.00017700134252524036,
                    "stat": 0.00016186214642142918,
                    "syst": 0.0030937480887346294,
                    "tagIso": 0.0030833494099694603,
                    "value": 0.9886048404057468
                },
                "pt:[50,60]": {
                    "AltSig": 0.0007071272262785255,
                    "massBin": 0.0004777461419189222,
                    "massRange": 0.00025083931873692844,
                    "stat": 0.00034588172269190304,
                    "syst": 0.0030252050155484215,
                    "tagIso": 0.0028914831370789873,
                    "value": 0.9883825526731891
                },
                "pt:[60,120]": {
                    "AltSig": 0.00016384540088798527,
                    "massBin": 0.0007988294247784911,
                    "massRange": 0.0002681159644080666,
                    "stat": 0.0007582024379362086,
                    "syst": 0.0018220896942101226,
                    "tagIso": 0.0016072183790923344,
                    "value": 0.9891550629912294
                }
            },
            "abseta:[1.2,2.1]": {
                "pt:[15,20]": {
                    "AltSig": 0.0010648753784150422,
                    "massBin": 0.00029837109452057753,
                    "massRange": 0.0002824039559387592,
                    "stat": 0.0005404211394419734,
                    "syst": 0.005138608867602577,
                    "tagIso": 0.005010245923931678,
                    "value": 0.9938372128237783
                },
                "pt:[20,25]": {
                    "AltSig": 0.0011456605254126506,
                    "massBin": 0.0002990310593860013,
                    "massRange": 0.0003292582227975016,
                    "stat": 0.00030551406817022083,
                    "syst": 0.0038356905944420547,
                    "tagIso": 0.003633476812234415,
                    "value": 0.9931941863357674
                },
                "pt:[25,30]": {
                    "AltSig": 0.0004711062511937314,
                    "massBin": 0.00028811872089257173,
                    "massRange": 0.00016913631283477226,
                    "stat": 0.00019714746493556067,
                    "syst": 0.004312671527509596,
                    "tagIso": 0.004273824413172589,
                    "value": 0.9945286868964238
                },
                "pt:[30,40]": {
                    "AltSig": 0.000358120043138177,
                    "massBin": 3.526397097558531e-05,
                    "massRange": 6.235812476268476e-05,
                    "stat": 9.80072267016338e-05,
                    "syst": 0.003987881972778424,
                    "tagIso": 0.003971123339829796,
                    "value": 0.9946328354518277
                },
                "pt:[40,50]": {
                    "AltSig": 0.0001002443586466395,
                    "massBin": 6.44066573823876e-06,
                    "massRange": 2.7893072479745484e-05,
                    "stat": 8.553454007244182e-05,
                    "syst": 0.0030023169491755273,
                    "tagIso": 0.003000506394960467,
                    "value": 0.995614658914937
                },
                "pt:[50,60]": {
                    "AltSig": 0.0012083008857682875,
                    "massBin": 0.00032500639188970393,
                    "massRange": 4.198321691550877e-05,
                    "stat": 0.00018246679345115187,
                    "syst": 0.002958409081649744,
                    "tagIso": 0.0026804480070629078,
                    "value": 0.9951795488238614
                },
                "pt:[60,120]": {
                    "AltSig": 0.0011182813310132156,
                    "massBin": 9.688429065635162e-05,
                    "massRange": 0.00019248996334741975,
                    "stat": 0.0002924624723865122,
                    "syst": 0.0023931240259481563,
                    "tagIso": 0.002104768518510325,
                    "value": 0.9949115051768846
                }
            },
            "abseta:[2.1,2.4]": {
                "pt:[15,20]": {
                    "AltSig": 0.005148021019008908,
                    "massBin": 0.0009766048713836795,
                    "massRange": 0.0011960554710455096,
                    "stat": 0.0013157554620058548,
                    "syst": 0.006700739096955697,
                    "tagIso": 0.004001684428923014,
                    "value": 0.9868032932289676
                },
                "pt:[20,25]": {
                    "AltSig": 0.0035562335500342046,
                    "massBin": 0.001302976329850547,
                    "massRange": 0.0007323912282785616,
                    "stat": 0.0007976263381122166,
                    "syst": 0.005778038914992029,
                    "tagIso": 0.004301719704183804,
                    "value": 0.9886373069832018
                },
                "pt:[25,30]": {
                    "AltSig": 0.0029658679023260026,
                    "massBin": 5.23614894125668e-05,
                    "massRange": 0.0006290302552346416,
                    "stat": 0.0005069660427044143,
                    "syst": 0.005670346838161211,
                    "tagIso": 0.0047914549004893225,
                    "value": 0.9893837238145569
                },
                "pt:[30,40]": {
                    "AltSig": 0.0016366653496542316,
                    "massBin": 1.0803710224771557e-05,
                    "massRange": 0.0004579149826534623,
                    "stat": 0.0002598429612791979,
                    "syst": 0.0044279079821768095,
                    "tagIso": 0.004088751983230721,
                    "value": 0.9897229489202066
                },
                "pt:[40,50]": {
                    "AltSig": 0.0020131523976736343,
                    "massBin": 2.2601655472576088e-05,
                    "massRange": 7.021736793649813e-05,
                    "stat": 0.0002771348418794196,
                    "syst": 0.004129429171350246,
                    "tagIso": 0.0036047137738451918,
                    "value": 0.991386944913452
                },
                "pt:[50,60]": {
                    "AltSig": 0.003142834194213018,
                    "massBin": 0.00040061563138621414,
                    "massRange": 0.0006135225011300038,
                    "stat": 0.0006457966033306104,
                    "syst": 0.004767933168500256,
                    "tagIso": 0.003509825805288136,
                    "value": 0.991062285112936
                },
                "pt:[60,120]": {
                    "AltSig": 0.0027635325474772987,
                    "massBin": 0.00015153087556679656,
                    "massRange": 0.0013786405326381423,
                    "stat": 0.0011642820078733422,
                    "syst": 0.01408342040081564,
                    "tagIso": 0.01373979645848733,
                    "value": 0.9938546977939712
                }
            }
        }
    }
}
